hcraft/__init__.py
hcraft/__main__.py
hcraft/cli.py
hcraft/elements.py
hcraft/env.py
hcraft/metrics.py
hcraft/planning.py
hcraft/purpose.py
hcraft/requirements.py
hcraft/solving_behaviors.py
hcraft/state.py
hcraft/task.py
hcraft/transformation.py
hcraft/world.py
hcraft/behaviors/__init__.py
hcraft/behaviors/actions.py
hcraft/behaviors/behaviors.py
hcraft/behaviors/feature_conditions.py
hcraft/behaviors/utils.py
hcraft/examples/__init__.py
hcraft/examples/light_recursive.py
hcraft/examples/recursive.py
hcraft/examples/tower.py
hcraft/examples/minecraft/__init__.py
hcraft/examples/minecraft/env.py
hcraft/examples/minecraft/items.py
hcraft/examples/minecraft/tools.py
hcraft/examples/minecraft/transformations.py
hcraft/examples/minecraft/zones.py
hcraft/examples/minecraft/resources/font.ttf
hcraft/examples/minecraft/resources/items/blaze_powder.png
hcraft/examples/minecraft/resources/items/blaze_rod.png
hcraft/examples/minecraft/resources/items/book.png
hcraft/examples/minecraft/resources/items/clock.png
hcraft/examples/minecraft/resources/items/close_ender_portal.png
hcraft/examples/minecraft/resources/items/close_nether_portal.png
hcraft/examples/minecraft/resources/items/coal.png
hcraft/examples/minecraft/resources/items/cobblestone.png
hcraft/examples/minecraft/resources/items/crafting_table.png
hcraft/examples/minecraft/resources/items/diamond.png
hcraft/examples/minecraft/resources/items/diamond_axe.png
hcraft/examples/minecraft/resources/items/diamond_pickaxe.png
hcraft/examples/minecraft/resources/items/diamond_shovel.png
hcraft/examples/minecraft/resources/items/diamond_sword.png
hcraft/examples/minecraft/resources/items/dirt.png
hcraft/examples/minecraft/resources/items/egg.png
hcraft/examples/minecraft/resources/items/enchanting_table.png
hcraft/examples/minecraft/resources/items/ender_dragon_head.png
hcraft/examples/minecraft/resources/items/ender_eye.png
hcraft/examples/minecraft/resources/items/ender_pearl.png
hcraft-2.0.0.dist-info/LICENSE
hcraft-2.0.0.dist-info/METADATA
hcraft-2.0.0.dist-info/WHEEL
hcraft-2.0.0.dist-info/entry_points.txt
hcraft-2.0.0.dist-info/top_level.txt
hcraft-2.0.0.dist-info/RECORD
