Metadata-Version: 2.2
Name: hcraft
Version: 2.0.0
Summary: Lightweight environments to study hierarchical reasoning
Author: Mathïs Fédérico
Author-email: Mathïs Fédérico <mathfederico@gmail.com>
License: GNU General Public License v3 or later (GPLv3+)
Project-URL: Source, https://github.com/IRLL/HierarchyCraft
Keywords: gym,hcraft,minecraft,hierachical,reinforcement,learning
Requires-Python: >=3.8
License-File: LICENSE
Requires-Dist: numpy
Requires-Dist: networkx>=2.5.1
Requires-Dist: matplotlib
Requires-Dist: seaborn
Requires-Dist: hebg>=0.2.3
Provides-Extra: gym
Requires-Dist: gymnasium>=1.0.0; extra == "gym"
Provides-Extra: gui
Requires-Dist: pygame>=2.1.0; extra == "gui"
Requires-Dist: pygame-menu>=4.3.8; extra == "gui"
Provides-Extra: planning
Requires-Dist: unified_planning[aries,enhsp]>=1.1.0; extra == "planning"
Requires-Dist: up-enhsp>=0.0.25; extra == "planning"
Provides-Extra: htmlvis
Requires-Dist: pyvis<=0.3.1; extra == "htmlvis"
Provides-Extra: docs
Requires-Dist: pdoc>=14.7.0; extra == "docs"
